cognitoctl/__init__.py
cognitoctl/__main__.py
cognitoctl/commands/__init__.py
cognitoctl/commands/config.py
cognitoctl/commands/group.py
cognitoctl/commands/user.py
cognitoctl/config/__init__.py
cognitoctl/config/config.py
cognitoctl/exceptions/__init__.py
cognitoctl/exceptions/exceptions.py
cognitoctl/main.py
cognitoctl-1.0.0.dist-info/LICENSE
cognitoctl-1.0.0.dist-info/METADATA
cognitoctl-1.0.0.dist-info/WHEEL
cognitoctl-1.0.0.dist-info/entry_points.txt
cognitoctl-1.0.0.dist-info/RECORD
