Metadata-Version: 2.1
Name: cognitoctl
Version: 1.0.0
Summary: CLI to use aws cognito in a simple way
Home-page: https://github.com/DaniMG95/cognitoctl
Keywords: aws,cognito,authentication,authorization,python,cli
Author: Daniel Muñoz Gonzalez
Author-email: dani16595@gmail.com
Requires-Python: >=3.10.0,<4.0.0
Classifier: Programming Language :: Python :: 3
Classifier: Programming Language :: Python :: 3.10
Classifier: Programming Language :: Python :: 3.11
Classifier: Programming Language :: Python :: 3.12
Classifier: Programming Language :: Python :: 3.13
Requires-Dist: click (>=8.1.7,<9.0.0)
Requires-Dist: cognitopy (==1.1.6)
Requires-Dist: toml (>=0.10.2,<0.11.0)
Project-URL: Documentation, https://github.com/DaniMG95/cognitoctl/blob/main/README.md
Project-URL: Repository, https://github.com/DaniMG95/cognitoctl
